ps_request/__init__.py
ps_request/request.py
sp_requests-0.0.1.dist-info/METADATA
sp_requests-0.0.1.dist-info/WHEEL
sp_requests-0.0.1.dist-info/licence
sp_requests-0.0.1.dist-info/top_level.txt
sp_requests-0.0.1.dist-info/RECORD
